dexter/__init__.py
dexter/config/AnnConstants.py
dexter/config/LLmConstants.py
dexter/config/__init__.py
dexter/config/constants.py
dexter/data/__init__.py
dexter/data/datastructures/__init__.py
dexter/data/datastructures/answer.py
dexter/data/datastructures/dataset.py
dexter/data/datastructures/evidence.py
dexter/data/datastructures/question.py
dexter/data/datastructures/sample.py
dexter/data/datastructures/hyperparameters/__init__.py
dexter/data/datastructures/hyperparameters/base.py
dexter/data/datastructures/hyperparameters/dpr.py
dexter/data/loaders/AmbigQADataLoader.py
dexter/data/loaders/BaseDataLoader.py
dexter/data/loaders/DataLoaderFactory.py
dexter/data/loaders/DprDataLoader.py
dexter/data/loaders/FinQADataLoader.py
dexter/data/loaders/MusiqueQaDataLoader.py
dexter/data/loaders/OTTQADataLoader.py
dexter/data/loaders/RetrieverDataset.py
dexter/data/loaders/StrategyQADataLoader.py
dexter/data/loaders/TATQADataLoader.py
dexter/data/loaders/Tokenizer.py
dexter/data/loaders/WikiMultihopQADataLoader.py
dexter/data/loaders/__init__.py
dexter/llms/__init__.py
dexter/llms/flant5_engine.py
dexter/llms/llama_engine.py
dexter/llms/llm_engine_orchestrator.py
dexter/llms/mistral_engine.py
dexter/llms/openai_engine.py
dexter/re_ranker/CrossEncoder.py
dexter/re_ranker/ReRanker.py
dexter/re_ranker/__init__.py
dexter/retriever/BaseRetriever.py
dexter/retriever/__init__.py
dexter/retriever/dense/ANCE.py
dexter/retriever/dense/Baleen.py
dexter/retriever/dense/Contriever.py
dexter/retriever/dense/DenseFullSearch.py
dexter/retriever/dense/DprSentSearch.py
dexter/retriever/dense/HfRetriever.py
dexter/retriever/dense/TCTColBERT.py
dexter/retriever/dense/__init__.py
dexter/retriever/dense/ColBERT/__init__.py
dexter/retriever/dense/ColBERT/server.py
dexter/retriever/dense/ColBERT/setup.py
dexter/retriever/dense/ColBERT/build/__init__.py
dexter/retriever/dense/ColBERT/build/lib/__init__.py
dexter/retriever/dense/ColBERT/build/lib/colbert/__init__.py
dexter_cqa-1.0.9.dist-info/LICENSE.md
dexter_cqa-1.0.9.dist-info/METADATA
dexter_cqa-1.0.9.dist-info/WHEEL
dexter_cqa-1.0.9.dist-info/top_level.txt
dexter_cqa-1.0.9.dist-info/RECORD
