Metadata-Version: 2.1
Name: dexter-cqa
Version: 1.0.9
Summary: A Benchmark for Complex Heterogeneous Question answering
Home-page: https://github.com/VenkteshV/BCQA
Download-URL: 
Author: Venktesh V, Deepali Prabhu
Author-email: venkyviswa12@gmail.com
License: Apache License 2.0
Keywords: Information Retrieval Transformer Networks Complex Question Answering BERT PyTorch Question Answering IR NLP deep learning
Classifier: Development Status :: 4 - Beta
Classifier: Intended Audience :: Science/Research
Classifier: License :: OSI Approved :: Apache Software License
Classifier: Programming Language :: Python :: 3.8
Classifier: Topic :: Scientific/Engineering :: Artificial Intelligence
Requires-Python: >=3.8
License-File: LICENSE.md
Requires-Dist: sentence-transformers
Requires-Dist: pytrec-eval
Requires-Dist: faiss-cpu
Requires-Dist: elasticsearch ==7.9.1
Requires-Dist: data
Requires-Dist: toml
Requires-Dist: zope.interface
Requires-Dist: transformers ==4.30.0
Requires-Dist: protobuf
Requires-Dist: openai
Requires-Dist: annoy
Requires-Dist: joblib
Requires-Dist: tqdm
Requires-Dist: pandas
Requires-Dist: ujson
Requires-Dist: gitpython
Provides-Extra: tf
Requires-Dist: tensorflow >=2.2.0 ; extra == 'tf'
Requires-Dist: tensorflow-text ; extra == 'tf'
Requires-Dist: tensorflow-hub ; extra == 'tf'
